msgpack/__init__.py
msgpack/_packer.so
msgpack/_packer_py.py
msgpack/_unpacker.so
msgpack/_version.py
msgpack/exceptions.py
msgpack/fallback.py
msgpack/setup.py
msgpack_rlp_python-0.5.8.dist-info/METADATA
msgpack_rlp_python-0.5.8.dist-info/RECORD
msgpack_rlp_python-0.5.8.dist-info/WHEEL
msgpack_rlp_python-0.5.8.dist-info/top_level.txt
