Metadata-Version: 2.1
Name: msgpack-rlp-python
Version: 0.5.8
Summary: MessagePack (de)serializer with Ethereum RLP encoding
Home-page: https://heliosprotocol.io/
Author: INADA Naoki, Tommy Mckinnon
Author-email: songofacandy@gmail.com, admin@hyperevo.com
License: Apache 2.0
Project-URL: Source, https://github.com/Helios-Protocol/msgpack-rlp-python
Project-URL: Tracker, https://github.com/Helios-Protocol/msgpack-rlp-python/issues
Platform: UNKNOWN
Classifier: Programming Language :: Python :: 2
Classifier: Programming Language :: Python :: 2.7
Classifier: Programming Language :: Python :: 3
Classifier: Programming Language :: Python :: 3.5
Classifier: Programming Language :: Python :: 3.6
Classifier: Programming Language :: Python :: 3.7
Classifier: Programming Language :: Python :: Implementation :: CPython
Classifier: Programming Language :: Python :: Implementation :: PyPy
Classifier: Intended Audience :: Developers
Classifier: License :: OSI Approved :: Apache Software License
